loupe/__init__.py
loupe/core.py
loupe/cost.py
loupe/einsum.py
loupe/fourier.py
loupe/numeric.py
loupe/optimize.py
loupe/shape.py
loupe/special.py
loupe/tensordot.py
loupe/util.py
loupe/zernike.py
Loupe-1.3.1.dist-info/LICENSE
Loupe-1.3.1.dist-info/METADATA
Loupe-1.3.1.dist-info/NOTICE
Loupe-1.3.1.dist-info/WHEEL
Loupe-1.3.1.dist-info/top_level.txt
Loupe-1.3.1.dist-info/RECORD
