Metadata-Version: 2.1
Name: Loupe
Version: 1.3.1
Summary: A Python library for solving parametric optimization problems with built-in autograd.
Home-page: https://loupe.readthedocs.io
Author: Andy Kee
License: BSD-3-Clause
Project-URL: Documentation, https://loupe.readthedocs.io
Project-URL: Code, https://github.com/andykee/loupe
Project-URL: Issue tracker, https://github.com/andykee/loupe/issues
Classifier: Development Status :: 4 - Beta
Classifier: Intended Audience :: Science/Research
Classifier: License :: OSI Approved :: BSD License
Classifier: Programming Language :: Python :: 3
Classifier: Topic :: Scientific/Engineering :: Astronomy
Classifier: Topic :: Scientific/Engineering :: Image Processing
Classifier: Topic :: Scientific/Engineering :: Mathematics
Classifier: Topic :: Scientific/Engineering :: Physics
Requires-Python: >=3.6
License-File: LICENSE
License-File: NOTICE
Requires-Dist: numpy
Requires-Dist: scipy
